src/__init__.py
src/urlscanio/__init__.py
src/urlscanio/__main__.py
src/urlscanio/urlscan.py
src/urlscanio/utils.py
urlscanio-0.2.2.dist-info/LICENSE
urlscanio-0.2.2.dist-info/METADATA
urlscanio-0.2.2.dist-info/WHEEL
urlscanio-0.2.2.dist-info/entry_points.txt
urlscanio-0.2.2.dist-info/top_level.txt
urlscanio-0.2.2.dist-info/RECORD
