Metadata-Version: 2.1
Name: urlscanio
Version: 0.2.2
Summary: Command line utility to get information about a website using URLScan.io's APIs.
Home-page: https://github.com/Aquarthur/urlscanio
Author: Arthur Verkaik
Author-email: art.v412@gmail.com
License: MIT
Keywords: urlscan cli
Platform: UNKNOWN
Classifier: Development Status :: 4 - Beta
Classifier: Operating System :: OS Independent
Classifier: Programming Language :: Python :: 3.8
Classifier: Programming Language :: Python :: Implementation :: CPython
Requires-Python: >=3.8
License-File: LICENSE
Requires-Dist: aiohttp
Requires-Dist: aiofiles
